cfed/__init__.py
cfed/pairwise.py
tests/__init__.py
tests/test_pairwise.py
cfed-1.1.dist-info/LICENSE
cfed-1.1.dist-info/METADATA
cfed-1.1.dist-info/WHEEL
cfed-1.1.dist-info/top_level.txt
cfed-1.1.dist-info/RECORD
