Metadata-Version: 2.1
Name: cfed
Version: 1.1
Summary: A python package to compute pairwise Euclidean distances on datasets with categorical features in little time
Home-page: https://github.com/ItsWajdy/categorical_features_euclidean_distance
Author: Wajdy
Author-email: itswajdy@gmail.com
License: UNKNOWN
Platform: UNKNOWN
Classifier: Programming Language :: Python :: 3
Classifier: License :: OSI Approved :: MIT License
Classifier: Operating System :: OS Independent
Requires-Python: >=3.6
